clb/__init__.py
clb/config_parser.py
clb/logger.py
clb/shell_commands.py
clb/notifiers/__init__.py
clb/notifiers/influxdb_client.py
clb/notifiers/slack_client.py
clb/storages/__init__.py
clb/storages/aws_s3.py
clb-0.0.10.dist-info/LICENSE
clb-0.0.10.dist-info/METADATA
clb-0.0.10.dist-info/WHEEL
clb-0.0.10.dist-info/top_level.txt
clb-0.0.10.dist-info/RECORD
