Metadata-Version: 2.1
Name: clb
Version: 0.0.10
Summary: Command line batteries (clb) - the way to improve the functionality of Bash commands without writing a too difficult Bash code.
Home-page: https://github.com/daddy-shark/command_line_batteries
Author: Andrey Okulov
Author-email: okulov@ya.ru
License: UNKNOWN
Platform: UNKNOWN
Classifier: Intended Audience :: System Administrators
Classifier: Topic :: System :: Archiving :: Backup
Classifier: Development Status :: 3 - Alpha
Classifier: Programming Language :: Python :: 3
Classifier: Programming Language :: Python :: 3.6
Classifier: Programming Language :: Python :: 3.7
Classifier: License :: OSI Approved :: MIT License
Classifier: Operating System :: POSIX :: Linux
Requires-Dist: PyYAML (<6.0,>=5.1)
Requires-Dist: influxdb (<6.0,>=5.2.2)
Requires-Dist: boto3 (<2.0,>=1.9.120)
Requires-Dist: requests (<3.0,>=2.21.0)
Requires-Dist: slackclient (<3.0,>=2.0.1)
Provides-Extra: devel
Requires-Dist: mypy (>=0.701<1.0) ; extra == 'devel'
Requires-Dist: pylint (>=2.3.1<3.0) ; extra == 'devel'
Requires-Dist: pytest (>=4.4.1<5.0) ; extra == 'devel'
Requires-Dist: twine (>=1.13.0<2.0) ; extra == 'devel'
